mailgun/__init__.py
mailgun/_version.py
mailgun/client.py
mailgun/doc_tests/files/data.csv
mailgun/doc_tests/files/email_previews.csv
mailgun/doc_tests/files/email_validation.csv
mailgun/doc_tests/files/mailgun_bounces_test.csv
mailgun/doc_tests/files/mailgun_complaints.csv
mailgun/doc_tests/files/mailgun_unsubscribes.csv
mailgun/doc_tests/files/mailgun_whitelists.csv
mailgun/doc_tests/files/test1.txt
mailgun/doc_tests/files/test2.txt
mailgun/doc_tests/files/test_mime.mime
mailgun/examples/__init__.py
mailgun/examples/async_client_examples.py
mailgun/examples/bounce_classification_examples.py
mailgun/examples/credentials_examples.py
mailgun/examples/domain_examples.py
mailgun/examples/email_validation_examples.py
mailgun/examples/events_examples.py
mailgun/examples/inbox_placement_examples.py
mailgun/examples/ip_pools_examples.py
mailgun/examples/ips_examples.py
mailgun/examples/keys_examples.py
mailgun/examples/logs_examples.py
mailgun/examples/mailing_lists_examples.py
mailgun/examples/messages_examples.py
mailgun/examples/metrics_examples.py
mailgun/examples/routes_examples.py
mailgun/examples/suppressions_examples.py
mailgun/examples/tags_examples.py
mailgun/examples/tags_new_examples.py
mailgun/examples/templates_examples.py
mailgun/examples/users_examples.py
mailgun/examples/webhooks_examples.py
mailgun/handlers/__init__.py
mailgun/handlers/bounce_classification_handler.py
mailgun/handlers/default_handler.py
mailgun/handlers/domains_handler.py
mailgun/handlers/email_validation_handler.py
mailgun/handlers/error_handler.py
mailgun/handlers/inbox_placement_handler.py
mailgun/handlers/ip_pools_handler.py
mailgun/handlers/ips_handler.py
mailgun/handlers/keys_handler.py
mailgun/handlers/mailinglists_handler.py
mailgun/handlers/messages_handler.py
mailgun/handlers/metrics_handler.py
mailgun/handlers/routes_handler.py
mailgun/handlers/suppressions_handler.py
mailgun/handlers/tags_handler.py
mailgun/handlers/templates_handler.py
mailgun/handlers/users_handler.py
mailgun-1.6.0.dist-info/licenses/LICENSE
mailgun-1.6.0.dist-info/METADATA
mailgun-1.6.0.dist-info/WHEEL
mailgun-1.6.0.dist-info/top_level.txt
mailgun-1.6.0.dist-info/RECORD
