Metadata-Version: 2.4
Name: mailgun
Version: 1.6.0
Summary: Python SDK for Mailgun
Author-email: diskovod <diskovodik@gmail.com>, Mailgun <api@mailgun.com>
Maintainer-email: Serhii Kupriienko <kupriienko.serhii@gmail.com>
License-Expression: Apache-2.0
Project-URL: Documentation, https://documentation.mailgun.com
Project-URL: Homepage, https://www.mailgun.com
Project-URL: Issue Tracker, https://github.com/mailgun/mailgun-python/issues
Project-URL: Repository, https://github.com/mailgun/mailgun-python
Keywords: email python-wrapper,mailgun,Mailgun API Python Wrapper,mailgun-api,Python SDK for Mailgun,transactional-emails,wrapper
Classifier: Development Status :: 3 - Alpha
Classifier: Environment :: Console
Classifier: Intended Audience :: Developers
Classifier: Natural Language :: English
Classifier: Operating System :: OS Independent
Classifier: Programming Language :: Python :: 3 :: Only
Classifier: Programming Language :: Python :: 3.10
Classifier: Programming Language :: Python :: 3.11
Classifier: Programming Language :: Python :: 3.12
Classifier: Programming Language :: Python :: 3.13
Classifier: Programming Language :: Python :: 3.14
Classifier: Programming Language :: Python :: Implementation :: CPython
Classifier: Topic :: Communications :: Email
Classifier: Topic :: Utilities
Requires-Python: >=3.10
License-File: LICENSE
Requires-Dist: httpx>=0.24
Requires-Dist: requests>=2.32.5
Requires-Dist: typing-extensions>=4.7.1; python_version < "3.11"
Provides-Extra: conda-build
Requires-Dist: conda-build; extra == "conda-build"
Provides-Extra: docs
Requires-Dist: docconvert; extra == "docs"
Requires-Dist: pyment>=0.3.3; extra == "docs"
Provides-Extra: linting
Requires-Dist: autoflake; extra == "linting"
Requires-Dist: autopep8; extra == "linting"
Requires-Dist: bandit; extra == "linting"
Requires-Dist: black>=21.7; extra == "linting"
Requires-Dist: flake8>=3.7.8; extra == "linting"
Requires-Dist: isort; extra == "linting"
Requires-Dist: make; extra == "linting"
Requires-Dist: monkeytype; extra == "linting"
Requires-Dist: mypy; extra == "linting"
Requires-Dist: pandas-stubs; extra == "linting"
Requires-Dist: pep8-naming; extra == "linting"
Requires-Dist: pre-commit; extra == "linting"
Requires-Dist: pycodestyle; extra == "linting"
Requires-Dist: pydocstyle; extra == "linting"
Requires-Dist: pylint; extra == "linting"
Requires-Dist: pyright; extra == "linting"
Requires-Dist: python-dotenv>=0.19.2; extra == "linting"
Requires-Dist: pytype; extra == "linting"
Requires-Dist: pyupgrade; extra == "linting"
Requires-Dist: radon; extra == "linting"
Requires-Dist: refurb; extra == "linting"
Requires-Dist: ruff; extra == "linting"
Requires-Dist: safety; extra == "linting"
Requires-Dist: toml; extra == "linting"
Requires-Dist: types-pyyaml; extra == "linting"
Requires-Dist: types-requests; extra == "linting"
Requires-Dist: vulture; extra == "linting"
Requires-Dist: yapf; extra == "linting"
Provides-Extra: metrics
Requires-Dist: pystra; extra == "metrics"
Requires-Dist: wily>=1.2; extra == "metrics"
Provides-Extra: other
Requires-Dist: toml; extra == "other"
Provides-Extra: profilers
Requires-Dist: scalene>=1.3.16; extra == "profilers"
Requires-Dist: snakeviz; extra == "profilers"
Provides-Extra: spelling
Requires-Dist: typos; extra == "spelling"
Provides-Extra: tests
Requires-Dist: codecov; extra == "tests"
Requires-Dist: coverage>=4.5.4; extra == "tests"
Requires-Dist: openssl; extra == "tests"
Requires-Dist: pytest>=7; extra == "tests"
Requires-Dist: pytest-asyncio; extra == "tests"
Requires-Dist: pytest-benchmark; extra == "tests"
Requires-Dist: pytest-cov; extra == "tests"
Requires-Dist: pytest-order; extra == "tests"
Dynamic: license-file
